LICENSE
README.md
setup.py
redis_cluster/__init__.py
redis_cluster/redlock.py
redis_cluster_python.egg-info/PKG-INFO
redis_cluster_python.egg-info/SOURCES.txt
redis_cluster_python.egg-info/dependency_links.txt
redis_cluster_python.egg-info/requires.txt
redis_cluster_python.egg-info/top_level.txt