Metadata-Version: 2.1
Name: redis-cluster-python
Version: 0.0.2
Summary: This is my ctrip help package
Home-page: https://github.com/ckf10000/ctrip-helper
Author: ckf10000
Author-email: ckf10000@sina.com
Classifier: Programming Language :: Python :: 3
Classifier: License :: OSI Approved :: MIT License
Classifier: Operating System :: OS Independent
License-File: LICENSE
Requires-Dist: redis>=5.0.7
